{"cameraMode":{"drawMode":0,"name":"Shaded","section":"Shading Mode"},"sceneLighting":false,"audioPlay":false,"sceneViewState":{"showFog":true,"showMaterialUpdate":false,"showSkybox":false,"showFlares":true,"showImageEffects":true,"showParticleSystems":true},"in2DMode":false,"pivot":{"x":-0.022719621658325197,"y":1.319714069366455,"z":0.3696960210800171},"rotation":{"x":0.0015594025608152152,"y":0.9924204349517822,"z":0.12237586081027985,"w":-0.013108489103615284},"size":3.480694532394409,"orthographic":false}